mtml/__init__.py
mtml/core.py
my_test_ml-0.1.4.dist-info/licenses/LICENSE
my_test_ml-0.1.4.dist-info/METADATA
my_test_ml-0.1.4.dist-info/WHEEL
my_test_ml-0.1.4.dist-info/top_level.txt
my_test_ml-0.1.4.dist-info/RECORD
