Metadata-Version: 2.4
Name: my-test-ml
Version: 0.1.4
Summary: A test package for ML explanation utilities
Author-email: Cyruss Banerjee <cyruss.banerjee@proton.me>
License-Expression: MIT
Project-URL: Homepage, https://github.com/cyruss-banerjee/my-test-ml
Project-URL: Repository, https://github.com/cyruss-banerjee/my-test-ml
Keywords: machine-learning,explanation,test
Classifier: Programming Language :: Python :: 3
Classifier: Operating System :: OS Independent
Requires-Python: >=3.7
License-File: LICENSE
Requires-Dist: pyperclip
Dynamic: license-file
